subtitler/__init__.py
subtitler/__main__.py
subtitler/app.py
subtitler/audio.py
subtitler/decoding.py
subtitler/model.py
subtitler/timing.py
subtitler/tokenizer.py
subtitler/transcribe.py
subtitler/triton_ops.py
subtitler/utils.py
subtitler/version.py
subtitler/weight.py
subtitler/assets/gpt2.tiktoken
subtitler/assets/mel_filters.npz
subtitler/assets/multilingual.tiktoken
subtitler/normalizers/__init__.py
subtitler/normalizers/basic.py
subtitler/normalizers/english.json
subtitler/normalizers/english.py
go_subtitle-20231106.dist-info/LICENSE
go_subtitle-20231106.dist-info/METADATA
go_subtitle-20231106.dist-info/WHEEL
go_subtitle-20231106.dist-info/entry_points.txt
go_subtitle-20231106.dist-info/top_level.txt
go_subtitle-20231106.dist-info/RECORD
