Metadata-Version: 2.1
Name: go-subtitle
Version: 20231106
Summary: Generate subtitle from audio or video file
Home-page: https://github.com/RedHeartSecretMan/go_subtitle
Author: HaoDaXia
Author-email: wh18307094479@gmail.com
License: MIT
Requires-Python: >=3.8
License-File: LICENSE
Requires-Dist: torch
Requires-Dist: numba
Requires-Dist: numpy
Requires-Dist: tiktoken
Requires-Dist: more-itertools
Requires-Dist: tqdm
Requires-Dist: regex
Requires-Dist: ffmpeg-python >=0.2.0
Requires-Dist: filetype >=1.2.0
